LICENSE
circlepacker/__init__.py
circlepacker/__main__.py
circlepacker/domain/__init__.py
circlepacker/domain/circle.py
circlepacker/domain/contracts.py
circlepacker/domain/model.py
circlepacker/domain/solution_domain.py
circlepacker/domain/variables.py
circlepacker/optimization/__init__.py
circlepacker/optimization/solver.py
circlepacker/routers/__init__.py
circlepacker/routers/health.py
circlepacker/routers/solves.py
circlepacker/service.py
circlepacker-0.2.7.dist-info/LICENSE
circlepacker-0.2.7.dist-info/WHEEL
circlepacker-0.2.7.dist-info/METADATA
circlepacker-0.2.7.dist-info/RECORD
